Metadata-Version: 2.1
Name: mc920
Version: 0.1
Summary: Assignments of Image Processing Course (MC920)
Home-page: https://github.com/mauricio-lorenzetti/mc920
Author: Mauricio Lorenzetti
Author-email: mauricio.lorenzetti.bezerra@gmail.com
License: MIT
License-File: LICENSE.md
